AUTHORS
CHANGELOG
CONTRIBUTING.rst
MANIFEST.in
README.rst
VERSION
setup.py
example/manage.py
example/example/__init__.py
example/example/settings.py
example/example/urls.py
example/example/wsgi.py
example/subapp/__init__.py
example/subapp/admin.py
example/subapp/models.py
example/subapp/tests.py
example/subapp/views.py
example/subapp/templates/home.html
pimpmytheme/__init__.py
pimpmytheme/admin.py
pimpmytheme/context_processors.py
pimpmytheme/folder_management.py
pimpmytheme/models.py
pimpmytheme/static_finder.py
pimpmytheme/template_loader.py
pimpmytheme/tests.py
pimpmytheme/views.py
pimpmytheme.egg-info/PKG-INFO
pimpmytheme.egg-info/SOURCES.txt
pimpmytheme.egg-info/dependency_links.txt
pimpmytheme.egg-info/not-zip-safe
pimpmytheme.egg-info/requires.txt
pimpmytheme.egg-info/top_level.txt
pimpmytheme/management/__init__.py
pimpmytheme/management/commands/__init__.py
pimpmytheme/management/commands/create_folders.py