Metadata-Version: 1.1
Name: pimpmytheme
Version: 0.1-dev
Summary: Customise theme (css and template) on a per
Home-page: https://github.com/novapost/pimpmytheme
Author: Yohann Gabory
Author-email: yohann.gabory@novapost.fr
License: MIT License
Platform: UNKNOWN
Classifier: Development Status :: 4 - Beta
Classifier: Intended Audience :: Developers
Classifier: License :: OSI Approved :: MIT License
Classifier: Programming Language :: Python
Classifier: Programming Language :: Python :: 2
Classifier: Programming Language :: Python :: 2.7
Classifier: Programming Language :: Python :: 3
Classifier: Programming Language :: Python :: 3.3
